src/postgres/__init__.py
src/postgres/implementation_instructions.md
src/postgres/server.py
mseep_simple_psql_mcp-1.0.1.dist-info/METADATA
mseep_simple_psql_mcp-1.0.1.dist-info/WHEEL
mseep_simple_psql_mcp-1.0.1.dist-info/entry_points.txt
mseep_simple_psql_mcp-1.0.1.dist-info/licenses/LICENSE
mseep_simple_psql_mcp-1.0.1.dist-info/RECORD
