Metadata-Version: 2.4
Name: mseep-simple-psql-mcp
Version: 1.0.1
Summary: A PostgreSQL MCP server project
Author-email: mseep <support@skydeck.ai>
License-File: LICENSE
Requires-Python: >=3.13
Requires-Dist: aiohttp>=3.11.13
Requires-Dist: mcp[cli]>=1.3.0
Requires-Dist: pyyaml>=6.0.2
